moat/lib/cmd/__init__.py
moat/lib/cmd/_test.py
moat/lib/cmd/anyio.py
moat/lib/cmd/base.py
moat/lib/cmd/const.py
moat/lib/cmd/errors.py
moat/lib/cmd/msg.py
moat/lib/cmd/nest.py
moat/lib/cmd/stream.py
moat_lib_cmd-0.4.11.dist-info/licenses/LICENSE.txt
moat_lib_cmd-0.4.11.dist-info/METADATA
moat_lib_cmd-0.4.11.dist-info/WHEEL
moat_lib_cmd-0.4.11.dist-info/top_level.txt
moat_lib_cmd-0.4.11.dist-info/RECORD
